{"scriptId":"3","url":"deno:core/core.js","functions":[{"functionName":"assert","ranges":[{"startOffset":2738,"endOffset":2817,"count":12}],"isBlockCoverage":false},{"functionName":"reset","ranges":[{"startOffset":2821,"endOffset":2959,"count":1}],"isBlockCoverage":true},{"functionName":"numRecords","ranges":[{"startOffset":3021,"endOffset":3088,"count":2}],"isBlockCoverage":true},{"functionName":"size","ranges":[{"startOffset":3092,"endOffset":3187,"count":3}],"isBlockCoverage":true},{"functionName":"getMeta","ranges":[{"startOffset":3334,"endOffset":3556,"count":1},{"startOffset":3391,"endOffset":3417,"count":0}],"isBlockCoverage":true},{"functionName":"getOffset","ranges":[{"startOffset":3560,"endOffset":3795,"count":1},{"startOffset":3619,"endOffset":3645,"count":0},{"startOffset":3697,"endOffset":3794,"count":0}],"isBlockCoverage":true},{"functionName":"shift","ranges":[{"startOffset":4418,"endOffset":4848,"count":2},{"startOffset":4505,"endOffset":4642,"count":1},{"startOffset":4642,"endOffset":4693,"count":0},{"startOffset":4693,"endOffset":4847,"count":1}],"isBlockCoverage":true},{"functionName":"handleAsyncMsgFromRust","ranges":[{"startOffset":6264,"endOffset":6630,"count":1},{"startOffset":6317,"endOffset":6507,"count":2},{"startOffset":6377,"endOffset":6507,"count":1},{"startOffset":6559,"endOffset":6626,"count":0}],"isBlockCoverage":true},{"functionName":"asyncHandle","ranges":[{"startOffset":6973,"endOffset":7280,"count":1},{"startOffset":7137,"endOffset":7185,"count":0}],"isBlockCoverage":true},{"functionName":"opAsync","ranges":[{"startOffset":7284,"endOffset":8049,"count":1}],"isBlockCoverage":true},{"functionName":"asyncHandlers.<computed>","ranges":[{"startOffset":7614,"endOffset":7697,"count":1}],"isBlockCoverage":true},{"functionName":"","ranges":[{"startOffset":7810,"endOffset":7889,"count":1}],"isBlockCoverage":true},{"functionName":"opSync","ranges":[{"startOffset":8053,"endOffset":8335,"count":10},{"startOffset":8300,"endOffset":8312,"count":0}],"isBlockCoverage":true},{"functionName":"binOpBuildRequest","ranges":[{"startOffset":8790,"endOffset":8996,"count":4}],"isBlockCoverage":true},{"functionName":"binOpParseResult","ranges":[{"startOffset":9000,"endOffset":10320,"count":4},{"startOffset":9567,"endOffset":9802,"count":0},{"startOffset":9900,"endOffset":10319,"count":0}],"isBlockCoverage":true},{"functionName":"binOpSync","ranges":[{"startOffset":10524,"endOffset":10701,"count":4}],"isBlockCoverage":true},{"functionName":"","ranges":[{"startOffset":10619,"endOffset":10665,"count":4}],"isBlockCoverage":true},{"functionName":"jsonOpBuildRequest","ranges":[{"startOffset":11029,"endOffset":11314,"count":1}],"isBlockCoverage":true},{"functionName":"jsonOpParseResult","ranges":[{"startOffset":11318,"endOffset":11611,"count":7},{"startOffset":11434,"endOffset":11562,"count":0}],"isBlockCoverage":true},{"functionName":"jsonOpAsync","ranges":[{"startOffset":11615,"endOffset":11817,"count":1}],"isBlockCoverage":true},{"functionName":"","ranges":[{"startOffset":11716,"endOffset":11780,"count":1}],"isBlockCoverage":true},{"functionName":"jsonOpSync","ranges":[{"startOffset":11821,"endOffset":12015,"count":6}],"isBlockCoverage":true},{"functionName":"","ranges":[{"startOffset":11920,"endOffset":11978,"count":6}],"isBlockCoverage":true},{"functionName":"resources","ranges":[{"startOffset":12019,"endOffset":12084,"count":2}],"isBlockCoverage":true}]}